laboratory/__init__.py
laboratory/admin.py
laboratory/apps.py
laboratory/fields.py
laboratory/migrations/0001_initial.py
laboratory/migrations/0002_instrument_created_instrument_modified_and_more.py
laboratory/migrations/__init__.py
laboratory/models.py
laboratory/views.py
django_laboratory-0.0.1.dist-info/LICENSE
django_laboratory-0.0.1.dist-info/METADATA
django_laboratory-0.0.1.dist-info/WHEEL
django_laboratory-0.0.1.dist-info/RECORD
