Metadata-Version: 2.1
Name: django-laboratory
Version: 0.0.1
Summary: A Django application for managing collections of scientific instruments
Home-page: https://github.com/SSJenny90/django-laboratory
License: MIT
Keywords: django,laboratory,science,scientific instrument,research management
Author: Sam Jennings
Author-email: samuel.scott.jennings@gmail.com
Requires-Python: >=3.8,<4.0
Classifier: Development Status :: 3 - Alpha
Classifier: Framework :: Django :: 3.2
Classifier: Intended Audience :: Developers
Classifier: License :: OSI Approved :: BSD License
Classifier: License :: OSI Approved :: MIT License
Classifier: Natural Language :: English
Classifier: Programming Language :: Python :: 3
Classifier: Programming Language :: Python :: 3.8
Classifier: Programming Language :: Python :: 3.9
Classifier: Programming Language :: Python :: 3.10
Classifier: Programming Language :: Python :: 3.11
Classifier: Programming Language :: Python :: 3.8
Classifier: Programming Language :: Python :: 3.9
Requires-Dist: django (>=3.2)
Requires-Dist: django-model-utils (>=4.3.1,<5.0.0)
